pasta_man/__init__.py
pasta_man/__main__.py
pasta_man/pasta_man.py
pasta_man/architectures/__init__.py
pasta_man/architectures/gui.py
pasta_man/architectures/targets.py
pasta_man/architectures/terminal.py
pasta_man/self_launch_thread/Launcher.py
pasta_man/self_launch_thread/__init__.py
pasta_man/utilities/__init__.py
pasta_man/utilities/encryption.py
pasta_man/utilities/helptext.py
pasta_man/utilities/pasta_docs.py
pasta_man/utilities/pasta_menu.py
pasta_man/utilities/retransform.py
pasta_man/utilities/upgrade.py
pasta_man/utilities/Exceptions/TerminalExceptions.py
pasta_man/utilities/Exceptions/__init__.py
pasta_man/utilities/Exceptions/exceptions.py
pasta_man-1.1.5.dist-info/LICENSE
pasta_man-1.1.5.dist-info/METADATA
pasta_man-1.1.5.dist-info/WHEEL
pasta_man-1.1.5.dist-info/entry_points.txt
pasta_man-1.1.5.dist-info/top_level.txt
pasta_man-1.1.5.dist-info/RECORD
