Metadata-Version: 2.1
Name: pasta-man
Version: 1.1.5
Summary: Password Manager
Author-email: Soumyo Deep Gupta <deep.main.ac@gmail.com>, Sairam Pimple <sairampimple003@gmail.com>, Shubham Narendra Singh <shubh1122000@gmail.com>
Maintainer-email: Soumyo Deep Gupta <deep.main.ac@gmail.com>
License: MIT License
Project-URL: GitHub, https://github.com/d33pster/pasta-man
Project-URL: Issues, https://github.com/d33pster/pasta-man/issues
Project-URL: Documentation, https://d33pster.github.io/pasta-man/
Keywords: d33pster,pasta-man,passman,pastaman,password-manager,password manager,password,manager
Classifier: Development Status :: 4 - Beta
Classifier: Topic :: Software Development
Classifier: Topic :: Security
Classifier: Programming Language :: Python :: 3.10
Classifier: Programming Language :: Python :: 3.11
Classifier: Programming Language :: Python :: 3.12
Classifier: License :: OSI Approved :: MIT License
Classifier: Operating System :: OS Independent
Classifier: Intended Audience :: End Users/Desktop
Requires-Python: >=3.10
License-File: LICENSE
Requires-Dist: cryptography
Requires-Dist: pandas
Requires-Dist: colorama
Requires-Dist: tk
Requires-Dist: optioner >=1.5.2
Requires-Dist: pyperclip
Requires-Dist: ttkthemes
Requires-Dist: pyinstaller
Requires-Dist: wrapper-bar >=0.1.4
Requires-Dist: requests
